ZhihuWendaWeishenmeGanjueXianzaiQuanZhongguoDuZaiJiabanDaodiDuZaiJiaShenme/README.md
ZhihuWendaWeishenmeGanjueXianzaiQuanZhongguoDuZaiJiabanDaodiDuZaiJiaShenme/__init__.py
ZhihuWendaWeishenmeGanjueXianzaiQuanZhongguoDuZaiJiabanDaodiDuZaiJiaShenme/__main__.py
ZhihuWendaWeishenmeGanjueXianzaiQuanZhongguoDuZaiJiabanDaodiDuZaiJiaShenme/file.epub
ZhihuWendaWeishenmeGanjueXianzaiQuanZhongguoDuZaiJiabanDaodiDuZaiJiaShenme/index.html
ZhihuWendaWeishenmeGanjueXianzaiQuanZhongguoDuZaiJiabanDaodiDuZaiJiaShenme/css/__init__.py
ZhihuWendaWeishenmeGanjueXianzaiQuanZhongguoDuZaiJiabanDaodiDuZaiJiaShenme/css/annotations.css
ZhihuWendaWeishenmeGanjueXianzaiQuanZhongguoDuZaiJiabanDaodiDuZaiJiaShenme/css/main.css
ZhihuWendaWeishenmeGanjueXianzaiQuanZhongguoDuZaiJiabanDaodiDuZaiJiaShenme/css/normalize.css
ZhihuWendaWeishenmeGanjueXianzaiQuanZhongguoDuZaiJiabanDaodiDuZaiJiaShenme/css/popup.css
ZhihuWendaWeishenmeGanjueXianzaiQuanZhongguoDuZaiJiabanDaodiDuZaiJiaShenme/font/__init__.py
ZhihuWendaWeishenmeGanjueXianzaiQuanZhongguoDuZaiJiabanDaodiDuZaiJiaShenme/font/fontello.eot
ZhihuWendaWeishenmeGanjueXianzaiQuanZhongguoDuZaiJiabanDaodiDuZaiJiaShenme/font/fontello.svg
ZhihuWendaWeishenmeGanjueXianzaiQuanZhongguoDuZaiJiabanDaodiDuZaiJiaShenme/font/fontello.ttf
ZhihuWendaWeishenmeGanjueXianzaiQuanZhongguoDuZaiJiabanDaodiDuZaiJiaShenme/font/fontello.woff
ZhihuWendaWeishenmeGanjueXianzaiQuanZhongguoDuZaiJiabanDaodiDuZaiJiaShenme/img/__init__.py
ZhihuWendaWeishenmeGanjueXianzaiQuanZhongguoDuZaiJiabanDaodiDuZaiJiaShenme/img/annotator-glyph-sprite.png
ZhihuWendaWeishenmeGanjueXianzaiQuanZhongguoDuZaiJiabanDaodiDuZaiJiaShenme/img/annotator-icon-sprite.png
ZhihuWendaWeishenmeGanjueXianzaiQuanZhongguoDuZaiJiabanDaodiDuZaiJiaShenme/img/apple-touch-icon.png
ZhihuWendaWeishenmeGanjueXianzaiQuanZhongguoDuZaiJiabanDaodiDuZaiJiaShenme/img/cancelfullscreen.png
ZhihuWendaWeishenmeGanjueXianzaiQuanZhongguoDuZaiJiabanDaodiDuZaiJiaShenme/img/close.png
zhihu_wenda_weishenme_ganjue_xianzai_quan_zhongguo_du_zai_jiaban_daodi_du_zai_jia_shenme-2024.3.5.0.dist-info/METADATA
zhihu_wenda_weishenme_ganjue_xianzai_quan_zhongguo_du_zai_jiaban_daodi_du_zai_jia_shenme-2024.3.5.0.dist-info/WHEEL
zhihu_wenda_weishenme_ganjue_xianzai_quan_zhongguo_du_zai_jiaban_daodi_du_zai_jia_shenme-2024.3.5.0.dist-info/entry_points.txt
zhihu_wenda_weishenme_ganjue_xianzai_quan_zhongguo_du_zai_jiaban_daodi_du_zai_jia_shenme-2024.3.5.0.dist-info/top_level.txt
zhihu_wenda_weishenme_ganjue_xianzai_quan_zhongguo_du_zai_jiaban_daodi_du_zai_jia_shenme-2024.3.5.0.dist-info/RECORD
